pydispatch/__init__.py
pydispatch/aioutils.py
pydispatch/decorators.py
pydispatch/dispatch.py
pydispatch/properties.py
pydispatch/utils.py
python_dispatch-0.2.3.dist-info/WHEEL
python_dispatch-0.2.3.dist-info/METADATA
python_dispatch-0.2.3.dist-info/RECORD
