Metadata-Version: 2.4
Name: python-dispatch
Version: 0.2.3
Summary: Lightweight Event Handling Library for Python
Keywords: event,properties,dispatch
Author: Matthew Reid
Author-email: Matthew Reid <matt@nomadic-recording.com>
License-Expression: MIT
Classifier: Development Status :: 3 - Alpha
Classifier: Intended Audience :: Developers
Classifier: Operating System :: OS Independent
Classifier: Programming Language :: Python
Classifier: Topic :: Software Development
Classifier: Programming Language :: Python :: 3
Classifier: Programming Language :: Python :: 3.8
Classifier: Programming Language :: Python :: 3.9
Classifier: Programming Language :: Python :: 3.10
Classifier: Programming Language :: Python :: 3.11
Classifier: Programming Language :: Python :: 3.12
Classifier: Programming Language :: Python :: 3.13
Classifier: Programming Language :: Python :: 3.14
Classifier: Topic :: Software Development :: Libraries
Classifier: Topic :: Software Development :: Libraries :: Python Modules
Requires-Dist: importlib-metadata ; python_full_version < '3.8'
Requires-Python: >=3.8
Project-URL: Documentation, https://python-dispatch.readthedocs.io/
Project-URL: Download, https://pypi.org/project/python-dispatch/
Project-URL: Source, https://github.com/nocarryr/python-dispatch
Project-URL: Tracker, https://github.com/nocarryr/python-dispatch/issues
